<layout id="SessionLayout">
    <drawable id="SessionLayoutGrid" />
    <label id="BattValueLabel"
        x="82%" y="16%" color="Graphics.COLOR_BLACK"
        justification="Graphics.TEXT_JUSTIFY_CENTER"
        font="Graphics.FONT_TINY"
        text="" />
    <label id="TimerTitleLabel"
        x="25%" y="3%" color="Graphics.COLOR_WHITE"
        justification="Graphics.TEXT_JUSTIFY_LEFT"
        font="Graphics.FONT_TINY"
        text="@Strings.TimerTitle" />
    <label id="TimerLeftValueLabel"
        x="18%" y="16%" color="Graphics.COLOR_WHITE"
        justification="Graphics.TEXT_JUSTIFY_RIGHT"
        font="Graphics.FONT_MEDIUM"
        text="" />
    <label id="TimerRightValueLabel"
        x="20%" y="14%" color="Graphics.COLOR_WHITE"
        justification="Graphics.TEXT_JUSTIFY_LEFT"
        font="Graphics.FONT_NUMBER_MEDIUM"
        text="@Strings.TimerPlaceholder" />
    <label id="TimeOfDayTitleLabel"
        x="center" y="43%" color="Graphics.COLOR_WHITE"
        justification="Graphics.TEXT_JUSTIFY_CENTER"
        font="Graphics.FONT_TINY"
        text="@Strings.TimeOfDayTitle" />
    <label id="TimeOfDayValueLabel"
        x="center" y="54%" color="Graphics.COLOR_WHITE"
        justification="Graphics.TEXT_JUSTIFY_CENTER"
        font="Graphics.FONT_NUMBER_HOT"
        text="@Strings.TimeOfDayPlaceholder" />
    <label id="DiveCountValueLabel"
        x="center" y="84%" color="Graphics.COLOR_WHITE"
        justification="Graphics.TEXT_JUSTIFY_CENTER"
        font="Graphics.FONT_TINY"
        text="@Strings.DiveCountPlaceholder" />
</layout>
